imgproc/__init__.py
imgproc/cpp/Binarization.cpp
imgproc/cpp/Binarization.hpp
imgproc/cpp/LineSegmentation.cpp
imgproc/cpp/LineSegmentation.hpp
imgproc/cpp/Scanner.cpp
imgproc/cpp/Scanner.hpp
imgproc/cpp/main.cpp
text_seg-0.1.0.data/data/main.py
text_seg-0.1.0.dist-info/METADATA
text_seg-0.1.0.dist-info/WHEEL
text_seg-0.1.0.dist-info/top_level.txt
text_seg-0.1.0.dist-info/RECORD
